LICENSE
README.md
pypromptpay.py
test.py
pypromptpay.egg-info/PKG-INFO
pypromptpay.egg-info/SOURCES.txt
pypromptpay.egg-info/dependency_links.txt
pypromptpay.egg-info/not-zip-safe
pypromptpay.egg-info/requires.txt
pypromptpay.egg-info/top_level.txt
pypromptpay-0.5.2.dist-info/LICENSE
pypromptpay-0.5.2.dist-info/METADATA
pypromptpay-0.5.2.dist-info/WHEEL
pypromptpay-0.5.2.dist-info/top_level.txt
pypromptpay-0.5.2.dist-info/RECORD
