Metadata-Version: 2.1
Name: pypromptpay
Version: 0.5.2
Summary: PromptPay QR code in Python
Home-page: https://github.com/wannaphong/pypromptpay
Author: Wannaphong Phatthiyaphaibun
Author-email: wannaphong@kkumail.com
License: Apache Software License 2.0
Keywords: promptpay
Platform: UNKNOWN
Classifier: Development Status :: 5 - Production/Stable
Classifier: Intended Audience :: Developers
Classifier: License :: OSI Approved :: Apache Software License
Classifier: Programming Language :: Python :: Implementation
Requires-Dist: qrcode
Requires-Dist: CRC-ITU
Requires-Dist: crc16
